README.rst
setup.py
cutfiles/__init__.py
cutfiles/cutfiles.py
cutfiles.egg-info/PKG-INFO
cutfiles.egg-info/SOURCES.txt
cutfiles.egg-info/dependency_links.txt
cutfiles.egg-info/requires.txt
cutfiles.egg-info/top_level.txt