Metadata-Version: 1.2
Name: cutfiles
Version: 1.0.6
Summary: Cutting file tool.
Home-page: https://github.com/q1115749329/cutfiles
Author: 甄超锋
Author-email: 4535@sohu.com
License: UNKNOWN
Platform: UNKNOWN
Classifier: Programming Language :: Python :: 3
Classifier: License :: OSI Approved :: MIT License
Classifier: Operating System :: OS Independent
Requires-Python: >=3.5
